{
	"versions": {
		"4.0.0-alpha2": {
			"name": "botframework-connector",
			"version": "4.0.0-alpha2",
			"dependencies": {
				"ms-rest": "^2.2.0"
			},
			"devDependencies": {
				"@types/mocha": "^2.2.47",
				"@types/node": "^9.3.0",
				"codelyzer": "^4.1.0",
				"mocha": "^5.0.0",
				"nyc": "^11.4.1",
				"source-map-support": "^0.5.3",
				"ts-node": "^4.1.0"
			},
			"directories": {},
			"dist": {
				"integrity": "sha512-UPgZT5qWpueq/ckcc9A6bxKKfZXIUHfOPA7fKCAgba6jOkIcRZ9ok8XVAbO+eQFyCmxpjTxiJJSP/rCDA1RyXw==",
				"shasum": "3d8654a058c0a8bb9338152e50d27f7b197c2cd3",
				"tarball": "https://registry.npmjs.org/botframework-connector/-/botframework-connector-4.0.0-alpha2.tgz"
			}
		},
		"4.0.0-m1.0": {
			"name": "botframework-connector",
			"version": "4.0.0-m1.0",
			"dependencies": {
				"ms-rest": "^2.2.0"
			},
			"devDependencies": {
				"@types/mocha": "^2.2.47",
				"@types/node": "^9.3.0",
				"codelyzer": "^4.1.0",
				"mocha": "^5.0.0",
				"nyc": "^11.4.1",
				"source-map-support": "^0.5.3",
				"ts-node": "^4.1.0"
			},
			"directories": {},
			"dist": {
				"integrity": "sha512-/uMCmAAOV1N//kzMTXvQXUw5/qoIY10Z7ub1h7NJ166eKEkp7K5vjBCaNjNlgKZPLIDzoGwgvJH6Yp4xeXuJ9A==",
				"shasum": "2578d6c53bf10e6818efb265aedb166112c30441",
				"tarball": "https://registry.npmjs.org/botframework-connector/-/botframework-connector-4.0.0-m1.0.tgz"
			}
		},
		"4.0.0-m1.2": {
			"name": "botframework-connector",
			"version": "4.0.0-m1.2",
			"dependencies": {
				"ms-rest": "^2.2.0"
			},
			"devDependencies": {
				"@types/mocha": "^2.2.47",
				"@types/node": "^9.3.0",
				"codelyzer": "^4.1.0",
				"mocha": "^5.0.0",
				"nyc": "^11.4.1",
				"source-map-support": "^0.5.3",
				"ts-node": "^4.1.0"
			},
			"_hasShrinkwrap": false,
			"directories": {},
			"dist": {
				"integrity": "sha512-hN/LNaNUG37ERic64CMGS3JnliexrHqgKbrqJlIjEN/By7aK2tdtQ+LjYNMfweASRKwYn66nFbQb4q+qRr8vQQ==",
				"shasum": "19287f4677fa9910b29bc2c472c312ac8fd800d4",
				"tarball": "https://registry.npmjs.org/botframework-connector/-/botframework-connector-4.0.0-m1.2.tgz",
				"fileCount": 45,
				"unpackedSize": 457783
			}
		},
		"4.0.0-m1.5": {
			"name": "botframework-connector",
			"version": "4.0.0-m1.5",
			"dependencies": {
				"@types/request": "^2.47.0",
				"base64url": "^2.0.0",
				"botframework-schema": "^4.0.0-m1.5",
				"jsonwebtoken": "8.0.1",
				"ms-rest-js": "^0.2.5",
				"request": "2.83.0",
				"rsa-pem-from-mod-exp": "^0.8.4"
			},
			"devDependencies": {
				"@types/jsonwebtoken": "7.2.5",
				"@types/mocha": "^2.2.47",
				"@types/node": "^9.3.0",
				"codelyzer": "^4.1.0",
				"mocha": "^5.0.0",
				"nyc": "^11.4.1",
				"source-map-support": "^0.5.3",
				"ts-node": "^4.1.0"
			},
			"_hasShrinkwrap": false,
			"directories": {},
			"dist": {
				"integrity": "sha512-eO+BX5HTDkoFxy+lQljsp4+9tamJaC3BLu2T0CBydgb1fa5XyUo95tFRrqp+yq543mD9zBO0ajT8+H6KrjDbaQ==",
				"shasum": "edac1aa31e8c2441e6abce7329e9ecbd94d6c42e",
				"tarball": "https://registry.npmjs.org/botframework-connector/-/botframework-connector-4.0.0-m1.5.tgz",
				"fileCount": 72,
				"unpackedSize": 638811
			}
		},
		"4.0.0-m1.6": {
			"name": "botframework-connector",
			"version": "4.0.0-m1.6",
			"dependencies": {
				"@types/request": "^2.47.0",
				"base64url": "^2.0.0",
				"botframework-schema": "^4.0.0-m1.5",
				"jsonwebtoken": "8.0.1",
				"ms-rest-js": "^0.2.5",
				"request": "2.83.0",
				"rsa-pem-from-mod-exp": "^0.8.4"
			},
			"devDependencies": {
				"@types/jsonwebtoken": "7.2.5",
				"@types/mocha": "^2.2.47",
				"@types/node": "^9.3.0",
				"codelyzer": "^4.1.0",
				"mocha": "^5.0.0",
				"nyc": "^11.4.1",
				"source-map-support": "^0.5.3",
				"ts-node": "^4.1.0"
			},
			"_hasShrinkwrap": false,
			"directories": {},
			"dist": {
				"integrity": "sha512-ld/W5sRTrSZezuqJF//5bMD220Lc0+xPbT3e4f8bftr5ckFDWk39Zk+dKtrgXCtCW7fEh1ueTV2/fr2hg3iOIQ==",
				"shasum": "c85595328611dc5ef2ed3ffa251da50c8153bf80",
				"tarball": "https://registry.npmjs.org/botframework-connector/-/botframework-connector-4.0.0-m1.6.tgz",
				"fileCount": 72,
				"unpackedSize": 643407
			}
		},
		"4.0.0-m1.7": {
			"name": "botframework-connector",
			"version": "4.0.0-m1.7",
			"dependencies": {
				"@types/request": "^2.47.0",
				"base64url": "^2.0.0",
				"botframework-schema": "^4.0.0-m1.7",
				"jsonwebtoken": "8.0.1",
				"ms-rest-js": "^0.2.5",
				"request": "2.83.0",
				"rsa-pem-from-mod-exp": "^0.8.4"
			},
			"devDependencies": {
				"@types/jsonwebtoken": "7.2.5",
				"@types/mocha": "^2.2.47",
				"@types/node": "^9.3.0",
				"codelyzer": "^4.1.0",
				"mocha": "^5.0.0",
				"nyc": "^11.4.1",
				"source-map-support": "^0.5.3",
				"ts-node": "^4.1.0"
			},
			"_hasShrinkwrap": false,
			"directories": {},
			"dist": {
				"integrity": "sha512-vW7pSxnEKsumzu8/juWS+qjaE4uaz+CFmZB/adeEoprb3OG7u+v4HD/A/ywvgAeMLpcp162ZRuS4qacP+mUC/w==",
				"shasum": "d03b0d55b73ac5302eee275cd010f6001e743a03",
				"tarball": "https://registry.npmjs.org/botframework-connector/-/botframework-connector-4.0.0-m1.7.tgz",
				"fileCount": 71,
				"unpackedSize": 632282
			}
		},
		"4.0.0-m1.9": {
			"name": "botframework-connector",
			"version": "4.0.0-m1.9",
			"dependencies": {
				"@types/request": "^2.47.0",
				"base64url": "^2.0.0",
				"botframework-schema": "4.0.0-m1.9",
				"jsonwebtoken": "8.0.1",
				"ms-rest-js": "^0.2.5",
				"request": "2.83.0",
				"rsa-pem-from-mod-exp": "^0.8.4"
			},
			"devDependencies": {
				"@types/jsonwebtoken": "7.2.5",
				"@types/mocha": "^2.2.47",
				"@types/node": "^9.3.0",
				"codelyzer": "^4.1.0",
				"mocha": "^5.0.0",
				"nyc": "^11.4.1",
				"source-map-support": "^0.5.3",
				"ts-node": "^4.1.0"
			},
			"_hasShrinkwrap": false,
			"directories": {},
			"dist": {
				"integrity": "sha512-KcEqmDuNa6qvPQMgfQgnuCWcf2J+XgQ8Stvj7XtqM4upqpBU9YDEJGNQB3OY6clEhD4Rz6Lbsojo9LgQInfL1w==",
				"shasum": "d97ad35616eeb16eb62369403e248f5b7039f06a",
				"tarball": "https://registry.npmjs.org/botframework-connector/-/botframework-connector-4.0.0-m1.9.tgz",
				"fileCount": 68,
				"unpackedSize": 636299
			}
		},
		"4.0.0-m1.10": {
			"name": "botframework-connector",
			"version": "4.0.0-m1.10",
			"dependencies": {
				"@types/request": "^2.47.0",
				"base64url": "^2.0.0",
				"botframework-schema": "4.0.0-m1.10",
				"jsonwebtoken": "8.0.1",
				"ms-rest-js": "^0.2.5",
				"request": "2.83.0",
				"rsa-pem-from-mod-exp": "^0.8.4"
			},
			"devDependencies": {
				"@types/jsonwebtoken": "7.2.5",
				"@types/mocha": "^2.2.47",
				"@types/node": "^9.3.0",
				"codelyzer": "^4.1.0",
				"mocha": "^5.0.0",
				"nyc": "^11.4.1",
				"source-map-support": "^0.5.3",
				"ts-node": "^4.1.0"
			},
			"_hasShrinkwrap": false,
			"directories": {},
			"dist": {
				"integrity": "sha512-8Nd+ng31j13a/aCB1lS/rx4wkhKnuWq8A/wqswaS++3cOfYK85NAVtnMLuIAkCAZ0sAiMZFkchmKFAB1z5KaWQ==",
				"shasum": "e54c8374bb0ee25dc3245e9753d580f40718f74a",
				"tarball": "https://registry.npmjs.org/botframework-connector/-/botframework-connector-4.0.0-m1.10.tgz",
				"fileCount": 71,
				"unpackedSize": 636989
			}
		},
		"4.0.0-m2.1": {
			"name": "botframework-connector",
			"version": "4.0.0-m2.1",
			"dependencies": {
				"@types/request": "^2.47.0",
				"base64url": "^2.0.0",
				"botframework-schema": "4.0.0-m2.1",
				"jsonwebtoken": "8.0.1",
				"ms-rest-js": "^0.2.5",
				"request": "2.83.0",
				"rsa-pem-from-mod-exp": "^0.8.4"
			},
			"devDependencies": {
				"@types/jsonwebtoken": "7.2.5",
				"@types/mocha": "^2.2.47",
				"@types/node": "^9.3.0",
				"codelyzer": "^4.1.0",
				"mocha": "^5.0.0",
				"nyc": "^11.4.1",
				"dotenv": "^5.0.1",
				"source-map-support": "^0.5.3",
				"ts-node": "^4.1.0"
			},
			"_hasShrinkwrap": false,
			"directories": {},
			"dist": {
				"integrity": "sha512-Tqs65MfAiYzMZ+HGUyNYChG8dzXm3vpH6FnB6vsqWctpjO/N8fMPOXhqsGyGerNlGF1MHnU7hJdpJ7sbhl1mMw==",
				"shasum": "87156c7a938d78b3c820eed791f9ad12c940397b",
				"tarball": "https://registry.npmjs.org/botframework-connector/-/botframework-connector-4.0.0-m2.1.tgz",
				"fileCount": 114,
				"unpackedSize": 1044708
			}
		},
		"4.0.0-m2.2": {
			"name": "botframework-connector",
			"version": "4.0.0-m2.2",
			"dependencies": {
				"@types/jsonwebtoken": "7.2.5",
				"@types/request": "^2.47.0",
				"@types/node": "^9.3.0",
				"base64url": "^2.0.0",
				"botframework-schema": "4.0.0-m2.2",
				"jsonwebtoken": "8.0.1",
				"ms-rest-js": "^0.2.5",
				"request": "2.83.0",
				"rsa-pem-from-mod-exp": "^0.8.4"
			},
			"devDependencies": {
				"@types/mocha": "^2.2.47",
				"codelyzer": "^4.1.0",
				"mocha": "^5.0.0",
				"nyc": "^11.4.1",
				"dotenv": "^5.0.1",
				"source-map-support": "^0.5.3",
				"ts-node": "^4.1.0"
			},
			"_hasShrinkwrap": false,
			"directories": {},
			"dist": {
				"integrity": "sha512-kKx89hzUyB+w3G6dhr8Qv5JoXxs87pvUP9ii4RnKKpq+ysOB6sbIO7I7BgAr3QE40kBmoOKa1qsULm+WMxHTpg==",
				"shasum": "ae74c0363e48c817c9f9904993945584f997c144",
				"tarball": "https://registry.npmjs.org/botframework-connector/-/botframework-connector-4.0.0-m2.2.tgz",
				"fileCount": 114,
				"unpackedSize": 1044708
			}
		},
		"4.0.0-m3.0": {
			"name": "botframework-connector",
			"version": "4.0.0-m3.0",
			"dependencies": {
				"@types/jsonwebtoken": "7.2.5",
				"@types/request": "^2.47.0",
				"@types/node": "^9.3.0",
				"base64url": "^2.0.0",
				"botframework-schema": "4.0.0-m3.0",
				"jsonwebtoken": "8.0.1",
				"ms-rest-js": "^0.2.5",
				"request": "2.83.0",
				"rsa-pem-from-mod-exp": "^0.8.4"
			},
			"devDependencies": {
				"@types/mocha": "^2.2.47",
				"codelyzer": "^4.1.0",
				"mocha": "^5.0.0",
				"nyc": "^11.4.1",
				"dotenv": "^5.0.1",
				"source-map-support": "^0.5.3",
				"ts-node": "^4.1.0"
			},
			"_hasShrinkwrap": false,
			"directories": {},
			"dist": {
				"integrity": "sha512-3fQBAZzFs51pjgFOI1FBjqT9qGedZFGuNgkswxCFwSJMXM/VkYSZCwgmwLMpdwvzSMX8sqLx+20rwk0I3/trmw==",
				"shasum": "ec0845dfdce0c06beb896897a461f1a38508d08c",
				"tarball": "https://registry.npmjs.org/botframework-connector/-/botframework-connector-4.0.0-m3.0.tgz",
				"fileCount": 114,
				"unpackedSize": 1044708
			}
		},
		"4.0.0-m4.0": {
			"name": "botframework-connector",
			"version": "4.0.0-m4.0",
			"dependencies": {
				"@types/jsonwebtoken": "7.2.5",
				"@types/request": "^2.47.0",
				"@types/node": "^9.3.0",
				"base64url": "^2.0.0",
				"botframework-schema": "4.0.0-m4.0",
				"jsonwebtoken": "8.0.1",
				"ms-rest-js": "^0.2.5",
				"request": "2.83.0",
				"rsa-pem-from-mod-exp": "^0.8.4"
			},
			"devDependencies": {
				"@types/mocha": "^2.2.47",
				"codelyzer": "^4.1.0",
				"mocha": "^5.0.0",
				"nyc": "^11.4.1",
				"dotenv": "^5.0.1",
				"source-map-support": "^0.5.3",
				"ts-node": "^4.1.0"
			},
			"_hasShrinkwrap": false,
			"directories": {},
			"dist": {
				"integrity": "sha512-hDQRyTi2uxDdllOkrSmoIx0Tuj2A/UchyZ39w0FvCavCYDEwpftGNE61csh+36109/vMsZGdaJZ8/OjwKAFu1w==",
				"shasum": "36a0f65333bb347f073ef8d4d692ecbfa6dd4d3a",
				"tarball": "https://registry.npmjs.org/botframework-connector/-/botframework-connector-4.0.0-m4.0.tgz",
				"fileCount": 118,
				"unpackedSize": 1143574,
				"npm-signature": "-----BEGIN PGP SIGNATURE-----\r\nVersion: OpenPGP.js v3.0.4\r\nComment: https://openpgpjs.org\r\n\r\nwsFcBAEBCAAQBQJa4kMHCRA9TVsSAnZWagAA2PYP/jt60TgAGyzbqp/XxQVb\nTA7z98u+VcOlSZ4V+J71ez+L9+G0IG8xz8zSknPPg2iwUkFdiIWRBbT0IhVz\n3Fs8dbh5P42lmRMJAwp8JxEIJQNIcbfoCVPFRHOGeRWexveJ+ejPGC+2XBce\n0Bv08WrcMEVgKPxZPamtRPPLnYIarDMRVrLRsEQSjBd5dlMb/8TuxIbwUY+3\nBsHpIejPy1aoPZPAjjmnRCdi6+6d5tCv8qpJN8uNhNQhj9CNlF2Wc9VPtmXD\n2219kmz0cGYfz0VFxanMEJjB1y0+DHoRr2qpUj2qfLwLBlTwyk0pwNwMqRbA\nuiZCgUueO7gRiVd2FXpE1SXLoAfQ6sdZBkjaNr+1aAlKNkb1GcpfN+GzAL6B\nuPYsLhaaVuxOVoPhRtiXm93+xsz47pLmQo3+2kr9P1fMByuP3IN64rPxoA2O\nyqe5LMJuhbQcc9AHCoow2cTyib6qQ+2/xEwmLM4d6l+rnohhKW8ehwsQI++M\nb4n4ACe6VRmedaAozm9b4izxwQI8osKJvRa/nPiMm70zZPCEir6+QfXTqfNy\nJ+LtHGTR8Am9JzRDSJpDure/hFQxHfGuyF+QxuQUYouTn4aoPmKVXEPZPTA9\npNI7voz9WCnZQd8FiBZ7aOp+rqepY1TOIMD+X7C+lQ/r1hBdzxV1qgkZ3Eeu\nR1U2\r\n=gQmo\r\n-----END PGP SIGNATURE-----\r\n"
			}
		},
		"4.0.0-m4.1": {
			"name": "botframework-connector",
			"version": "4.0.0-m4.1",
			"dependencies": {
				"@types/jsonwebtoken": "7.2.5",
				"@types/request": "^2.47.0",
				"@types/node": "^9.3.0",
				"base64url": "^2.0.0",
				"botframework-schema": "4.0.0-m4.1",
				"jsonwebtoken": "8.0.1",
				"ms-rest-js": "^0.2.5",
				"request": "2.83.0",
				"rsa-pem-from-mod-exp": "^0.8.4"
			},
			"devDependencies": {
				"@types/mocha": "^2.2.47",
				"codelyzer": "^4.1.0",
				"mocha": "^5.0.0",
				"nyc": "^11.4.1",
				"dotenv": "^5.0.1",
				"source-map-support": "^0.5.3",
				"ts-node": "^4.1.0"
			},
			"_hasShrinkwrap": false,
			"directories": {},
			"dist": {
				"integrity": "sha512-UxFbOsLlWgL2HQeBHu7ef+SSxTz/Rovyk6yyTpg63Bb2bQl/TCkKbf/dWKW7+ma+sbZnpO8HEq2YaP0KkBDP2A==",
				"shasum": "2cb2a7f496e61138c4d0c061d4d74c0ec5bb595a",
				"tarball": "https://registry.npmjs.org/botframework-connector/-/botframework-connector-4.0.0-m4.1.tgz",
				"fileCount": 118,
				"unpackedSize": 1143574,
				"npm-signature": "-----BEGIN PGP SIGNATURE-----\r\nVersion: OpenPGP.js v3.0.4\r\nComment: https://openpgpjs.org\r\n\r\nwsFcBAEBCAAQBQJa47eYCRA9TVsSAnZWagAA4H0P/3WR5U5/zA0zfZuAdLQN\ncSG4GegW4Qk0NEAIy2F2jsdLZ07SRypZXn1J/sGzZBhYDj9nOeSuSifWNCuf\nsKgIY7VFbs8OGp/Eog1c89jEF1WsVcWj3Nki/6RrMPwZWPvs8EyEv2FmVUJV\n7qgsnZcvBAtK+nEvXIAIxdoqPEaJBlxYe0fy0blVX50kZ+9ySWaJtHbSYF3E\noOuA1onoKZiO9dEAT94SK65HUTuXAwFO796vhiu6AUQk3xHivM7G5g2nGuOc\nwqVuJqqzmJVupGWwa+xhxe2emCe6Y1zjYquz8nwR0ioj2j0Enu1TpfaPqmJJ\nRm0EVAhCkyMJ10JQBleD1BuepwYRKIJGNcBwhiDb4M5iZUedYp9McOCmNPlI\nDlb0DIvVlBBxwPZIJS63UELSPU0ZgWoRSAg7TA026ukIfRpaac6z2NLwgwkq\njaBapNOlDXE0V6WxvzC3hF8M1HekKKjTS2yH01pglykWsWygvDoOfqH5/80+\ngJ5gFn6xC3IEt5GYWSw/um0C99z4NMPGS42/BEYWFsaRjK6IuW1yJarvjqbU\nZ1QDMRNXqPHyrMaKh6+BWzyFcKfLIYTJr+Wqi91eHnlxbxNqKYuMzYv0j1iN\naEzX8RhTYClTljwtdKs75a3GbZVYxpOLAJqHrH20TXGuzLA2HaOW/wCL9WtX\n6Fqx\r\n=y/Uy\r\n-----END PGP SIGNATURE-----\r\n"
			}
		},
		"4.0.0-m4.2": {
			"name": "botframework-connector",
			"version": "4.0.0-m4.2",
			"dependencies": {
				"@types/jsonwebtoken": "7.2.5",
				"@types/request": "^2.47.0",
				"@types/node": "^9.3.0",
				"base64url": "^2.0.0",
				"botframework-schema": "4.0.0-m4.2",
				"jsonwebtoken": "8.0.1",
				"ms-rest-js": "^0.2.5",
				"request": "2.83.0",
				"rsa-pem-from-mod-exp": "^0.8.4"
			},
			"devDependencies": {
				"@types/mocha": "^2.2.47",
				"codelyzer": "^4.1.0",
				"mocha": "^5.0.0",
				"nyc": "^11.4.1",
				"dotenv": "^5.0.1",
				"source-map-support": "^0.5.3",
				"ts-node": "^4.1.0"
			},
			"_hasShrinkwrap": false,
			"directories": {},
			"dist": {
				"integrity": "sha512-SweOBjjvuhEr/mbPLMtWFiIclt1xAT9ezUx9lCS2iZsIa3vA/0eXOcrCgnqfP2SmRqySFbMgpLkqLKsTHO83Lg==",
				"shasum": "51471f4938da424a4541a159d889e3bf9279f009",
				"tarball": "https://registry.npmjs.org/botframework-connector/-/botframework-connector-4.0.0-m4.2.tgz",
				"fileCount": 118,
				"unpackedSize": 1170299,
				"npm-signature": "-----BEGIN PGP SIGNATURE-----\r\nVersion: OpenPGP.js v3.0.4\r\nComment: https://openpgpjs.org\r\n\r\nwsFcBAEBCAAQBQJa6RzxCRA9TVsSAnZWagAAUwQP/jrRfxkYcqaT8ttFm/AY\nhteQot94bVLR3VU6IFIkZ+ziH87HQIDaKzOwUaCuOBHypHQ9MvQjUmgid3mk\n9byk5y8VS3w+v2gKfd3g3nAUQ70lX3+dMghu+rVNki/fN218K1ecx8LPUvcF\nSb4Ke7hyF6O+VD6RJdytwl9eN8L86yZeXbeYMbExu2pEy69UL1+3IrvyUgZp\nX+yf8y4QW0XViama5XceJIasHfsQ2kOAQV08TSeCotXMNpOWmbqywekJpoi4\nRbptnABkhk+FetUQlBqlunbSr8d8HxRPi4rnweFm6xDcpoAmI2jML34DkU0H\n7IgvFfXitkqaEYExCoRqdDNvqq9QEN15VIDsTjQahyfgbPDhBv2y2d9A1xQ/\nklGQ/q8+RHefqoz/7+Jazh/HXC0HJ3mLhYmB/tk2md/kkBDkBNGaykc063FV\ncUvduAlUJYl9Ls2TRiG6WBn8QdYT7b+PHOmVIYK43wYP/8t7c5rSWtgD3zOR\nUoV+S5CPBGEGDCNKVMzIqlPpIXzXTjokXtdkQeWJdThLd/qno2qz51ZmpCal\nM9W31XGoLLqM+PTs2Kicjh2bMLhnOd7avlGOUTdi2KWBF9wfh+G7HZnJBU2n\nl3I/jyLpoXIPltFXYYV487U6IN8z4vYLVSj7Fu1GcjY1SahsxdU4gZIwChst\nfttW\r\n=rAVP\r\n-----END PGP SIGNATURE-----\r\n"
			}
		},
		"4.0.0-preview1.0": {
			"name": "botframework-connector",
			"version": "4.0.0-preview1.0",
			"dependencies": {
				"@types/jsonwebtoken": "7.2.5",
				"@types/request": "^2.47.0",
				"@types/node": "^9.3.0",
				"base64url": "^2.0.0",
				"botframework-schema": "4.0.0-preview1.0",
				"jsonwebtoken": "8.0.1",
				"ms-rest-js": "^0.2.5",
				"request": "2.83.0",
				"rsa-pem-from-mod-exp": "^0.8.4"
			},
			"devDependencies": {
				"@types/mocha": "^2.2.47",
				"codelyzer": "^4.1.0",
				"mocha": "^5.0.0",
				"nyc": "^11.4.1",
				"dotenv": "^5.0.1",
				"source-map-support": "^0.5.3",
				"ts-node": "^4.1.0"
			},
			"_hasShrinkwrap": false,
			"directories": {},
			"dist": {
				"integrity": "sha512-fL7TXqk4S2k3emlFJKWKR3XwrLeTuULV1cWhVPttsSECVg4/UryxmAKX2GAaLQV5J18nKP7S3IgXDXjcb/rnAg==",
				"shasum": "6042c594bbcbcec2169b187894c763ac4d7172d2",
				"tarball": "https://registry.npmjs.org/botframework-connector/-/botframework-connector-4.0.0-preview1.0.tgz",
				"fileCount": 118,
				"unpackedSize": 1170311,
				"npm-signature": "-----BEGIN PGP SIGNATURE-----\r\nVersion: OpenPGP.js v3.0.4\r\nComment: https://openpgpjs.org\r\n\r\nwsFcBAEBCAAQBQJa68iCCRA9TVsSAnZWagAA/9sQAIezT3j45vx7CeJfaNaE\nyvFM5Hh5rum/7VK3j0DuiFEt1Xej63Zmcc/JrAGQ82BSGSAqJLnVhgpnQCQg\nCbPhrP0N3WOopBRd5sQlbYN00+XspUFklH6nBzZGjggLTx7RwdThadT4zfCB\nFF1A1MDQZBxJXzqf5HckvXYC266/56xF5mEPgu8eSDj6Q64gSQpwPhZo83+E\nR/BEU5rAVm1Zd2uZccyujdAs5v/JAlAanZvGTZI7lNtDVfMYFV9hihrqwy9F\nbE5briqwGCHdR7fPSfWY9ZVvNaJEWfFXxlii7yihdRTDEYbYCpaFhJ4mq+sh\nGxOp5wGt2x1YWFiJDZ/k7mJ0xUPkdyEqdiW+hRDk5yX794IP36tsH6y7wTbb\n8QYcI7RtxA7Mdoqa7wXSxmsDYNqQ8Vb+zezt/TyG1KZBRFreoQ60CP9Bbds1\neBQxBWagXGpmHBEYwfPmOb4u6v+stn4EiTctFEkSeMX03V3E9HOdlRkfq5s5\nhAieerzj2SqNmCy5A6ODvZWBXXbzYcKevUvA1BJ7rpHDFxEi1vd/PLgj0mk8\nD65L2Qn9Bc598cbl24p9R30o7GPaNi21qrr31+zApA2yRXYZgI0UJaSjc9t0\npCjTwnZ9XxPfCLUHr+KANVGd/3HrI++YrMwKKW5BWT5k6HXhEhlk8VO13cCN\nO6qJ\r\n=2DOx\r\n-----END PGP SIGNATURE-----\r\n"
			}
		},
		"4.0.0-preview1.1": {
			"name": "botframework-connector",
			"version": "4.0.0-preview1.1",
			"dependencies": {
				"@types/jsonwebtoken": "7.2.5",
				"@types/request": "^2.47.0",
				"@types/node": "^9.3.0",
				"base64url": "^2.0.0",
				"botframework-schema": "4.0.0-preview1.1",
				"jsonwebtoken": "8.0.1",
				"ms-rest-js": "^0.2.5",
				"request": "2.83.0",
				"rsa-pem-from-mod-exp": "^0.8.4"
			},
			"devDependencies": {
				"@types/mocha": "^2.2.47",
				"codelyzer": "^4.1.0",
				"mocha": "^5.0.0",
				"nyc": "^11.4.1",
				"dotenv": "^5.0.1",
				"source-map-support": "^0.5.3",
				"ts-node": "^4.1.0"
			},
			"_hasShrinkwrap": false,
			"directories": {},
			"dist": {
				"integrity": "sha512-zLtCj6KsP/yjKZ4T7ELcS6C3Ux9T7xIF6sFUAXsT4mV45wf7GW0ZZ1cirvEQOYUUdT9zhb1CZ5/30qY1PB7eyg==",
				"shasum": "3372a5b78af2d3182f9745e8826d124a0923e25c",
				"tarball": "https://registry.npmjs.org/botframework-connector/-/botframework-connector-4.0.0-preview1.1.tgz",
				"fileCount": 118,
				"unpackedSize": 1170311,
				"npm-signature": "-----BEGIN PGP SIGNATURE-----\r\nVersion: OpenPGP.js v3.0.4\r\nComment: https://openpgpjs.org\r\n\r\nwsFcBAEBCAAQBQJa7QhgCRA9TVsSAnZWagAAH8IP/jr5CyD3JIZz536ECSEm\nTGBKr9/jG5dm6cVVFSpj0TAWEpnlrw6/B1S4zMgmiXnQZu7x4GxCQ7AkFHHl\nIMNwr8uvEC/24TK6w6mALwdKrbaKLTQQJyk2WMSKcegnJtzk7xKLJkG2ZaG3\n9I3ZyzyuhJSv1ReEog2y5MSRUokMR/CI4e7G6Nk3LlCw61ljpnonC9mmH5NB\niTFZqyNlDD/GdaIYiEHz6JAWRUti4je8Mmp6QX0+8g7ZwMLrgZWt2y8LzhJR\nnBpcSoiGAcObkzt1IT7eGmYF3jUeh4WzUo4NHCO0plnkaS5ICef4V+OgtyJQ\nsAw/1Fa8dWA73K87noWZMwqtToRaoQjCttE0iCE8GBmJP2tSfOF/2s1DIx2y\nxS7WTNFS3MudOyEYsQlF+dsZg7Qa9vtYkYntLZcniIZB7unp3gm2tt7xPtIx\nHGtSyzXXRi43zfZzQVpBHANrS2LsL10jRowWSWA18cdy9+42IZxQKFQkrAA8\niUoKTS9QmMGepmGkrULMvhbKdTqMxc8M+JB0hnE0u72RyOTERYlZBwDW3ePh\nwW/wLPvBqTUzK418Am1T+XXFhUtJWmHBz8E6QFYy6DSYrlCjkUBNVGvQVKe9\nf/icxwXbo3nxO271cuiK7Nevu6nnXkC2QFoyqtHp3WwgYK7pgSURDzx1WJf7\nobCH\r\n=DDbf\r\n-----END PGP SIGNATURE-----\r\n"
			}
		},
		"4.0.0-preview1.2": {
			"name": "botframework-connector",
			"version": "4.0.0-preview1.2",
			"dependencies": {
				"@types/jsonwebtoken": "7.2.5",
				"@types/request": "^2.47.0",
				"@types/node": "^9.3.0",
				"base64url": "^2.0.0",
				"botframework-schema": "4.0.0-preview1.2",
				"jsonwebtoken": "8.0.1",
				"ms-rest-js": "^0.2.5",
				"request": "2.83.0",
				"rsa-pem-from-mod-exp": "^0.8.4"
			},
			"devDependencies": {
				"@types/mocha": "^2.2.47",
				"codelyzer": "^4.1.0",
				"mocha": "^5.0.0",
				"nyc": "^11.4.1",
				"dotenv": "^5.0.1",
				"source-map-support": "^0.5.3",
				"ts-node": "^4.1.0"
			},
			"_hasShrinkwrap": false,
			"directories": {},
			"dist": {
				"integrity": "sha512-DhxVGpUPjI9l8YBgMGMGb3l7nN+jrvxVI9Xcc5DUYYn9VSp065NxnQFWBqBRDSvhUQSPofN00WcJymbwSbuYXA==",
				"shasum": "983eb2227b41ccf7ab43e8998015a0fcb9b482ed",
				"tarball": "https://registry.npmjs.org/botframework-connector/-/botframework-connector-4.0.0-preview1.2.tgz",
				"fileCount": 118,
				"unpackedSize": 1170311,
				"npm-signature": "-----BEGIN PGP SIGNATURE-----\r\nVersion: OpenPGP.js v3.0.4\r\nComment: https://openpgpjs.org\r\n\r\nwsFcBAEBCAAQBQJa78e7CRA9TVsSAnZWagAAbt4P/iElnivoBypsXF3NIeWI\nnguf07e6aurvPXqFaz4u1XWzIXj7TRNm631HVYpeEfL9QwyBAix8ik285Oac\ne8oBTKExjhsCBA9KOjeKykm8X3SbUXCHqHh9RCYkbwcumgbj68vz6q61cyo1\nvOTMgm1k+s/L9vW9E/rg7JdUL6sGZIFqK+/DOc6tTxa0sb3x9gncWAa4HTNH\njeHiK0O5+9dvBpS4MmLVqsX86RWL+ZGSAExlXBrNP2yXAdZIJXzJFSW6zqVR\n2V7zzqQ20XLM7Kyb2v5o7qz/9UPXF4rP8b0N2l+phEqAkoW0y+MYuABAy9CG\nuSMmTqJlV/s9nTK8VeduAPO1wvHOiTBreSI6U9/qfMSA3U2KOSf1AT4eYUz8\nFRhPnAWvoAqKuR8SalvUVVsbrmSoSDQKwCLFNT9ltICzy/DobhYbjZVE+lV2\nnIYpBPcmWG0uSgqsZtu1E8eED9CXfa0SSL/+Eb9yPl/wZsjbWCY6wCVhJS1F\n/bEXE2Win+yhobBh++7DEmLoAgF6osVmG6pfuaCMqBiDUO4ERFntN9QRL8CZ\n+gaAz82Tnew8uPJerQClW8vhGNXPbWzdSNYOt/wokXoL0V6I51zeVnGd9/LJ\nongEIc+JnfVcmaED1V39+/0q6k3FOIHz9Jg+DBRCBRhjOj5VcD2id4kfP20d\nMDET\r\n=ePCY\r\n-----END PGP SIGNATURE-----\r\n"
			}
		},
		"4.0.6": {
			"name": "botframework-connector",
			"version": "4.0.6",
			"dependencies": {
				"@types/jsonwebtoken": "7.2.5",
				"@types/node": "^9.3.0",
				"@types/request": "^2.47.0",
				"base64url": "^2.0.0",
				"botframework-schema": "^4.0.6",
				"jsonwebtoken": "8.0.1",
				"ms-rest-js": "0.2.8",
				"ms-rest-azure": "^2.5.0",
				"request": "2.83.0",
				"rsa-pem-from-mod-exp": "^0.8.4"
			},
			"devDependencies": {
				"@types/mocha": "^2.2.47",
				"codelyzer": "^4.1.0",
				"mocha": "^5.0.0",
				"nyc": "^11.4.1",
				"dotenv": "^5.0.1",
				"should": "^13.2.3",
				"source-map-support": "^0.5.3",
				"ts-node": "^4.1.0"
			},
			"_hasShrinkwrap": false,
			"directories": {},
			"dist": {
				"shasum": "bd0eb7c16a56731288ccc76e445823141615779c",
				"tarball": "https://registry.npmjs.org/botframework-connector/-/botframework-connector-4.0.6.tgz",
				"integrity": "sha512-0AOJ91u9+9yJo68VNeeplM+ivWoQgfMswc5EE0h1+r2GYlqMNMDoWaLxKnD1ZG4jUdCVpUXwzpYvaWFSBFa9AQ==",
				"fileCount": 91,
				"unpackedSize": 805600,
				"npm-signature": "-----BEGIN PGP SIGNATURE-----\r\nVersion: OpenPGP.js v3.0.4\r\nComment: https://openpgpjs.org\r\n\r\nwsFcBAEBCAAQBQJbpY/ZCRA9TVsSAnZWagAA/1sP/j4KB1kDuIPre63ZWJnW\njTEgQSONNcpYxu5gMw5QBQUoifkaJ5ruouVEMrv198xMQzyFc5r/2zW18gNb\nuTvtR8JuKQN9QAFKseOXC9I9P8X/52jew/M2h7HqJM8b+ocRvGndk3h6KkFm\nU7a3O6M556jN4m4RzQaY9rkI8VvLDxtEKnLKgnY2/6l4iTSsWx3GdBYIVSAO\nSX7WqSe0rgYRWxdB45LDlcG1xqUwEMYxM8dTojaIsQWbuAIG+jdEjnabjQ4U\n+3+IcSAC6WIZWuGKs4T8DlVfPibNJxz+2IE3kiXeHWfDndlPeM64fWeUyuTY\nKYQPjilhLpGtZhv2kVABr/kC5BmPx2ToFlZF23Ky+kxY+FoJKIAA2OQBEaR2\ncnWeAbw3hpx2AcLPlFIV3yn2b7Xnh4ewVa26VDIrTV3k5hCtgyUQktpiIpWg\nqAJwbQgU7+CMyvzF2ZhKIqSxLOv7cp2YLNLYiCa8fduwiOLs5SYpgGpTkewA\niaZtqnpWxm/BTVEEUD8nGvDkzuATGs5999nL12wxU1VkMCVWsq8Egmv3LwRJ\nkNeudc+2Ee82wPqLqxR6j/85KTqrKClMI2EfbM+dF+Vu223drXZZVD8Ux8vf\naKIQjDztZNNr+ylMUFgx1FC3RqArDElOloaxruahxtZcc/m4tiX9Z67u4Nz9\nf/rs\r\n=wh5u\r\n-----END PGP SIGNATURE-----\r\n"
			}
		},
		"4.0.8": {
			"name": "botframework-connector",
			"version": "4.0.8",
			"dependencies": {
				"@types/jsonwebtoken": "7.2.5",
				"@types/node": "^9.3.0",
				"@types/request": "^2.47.0",
				"base64url": "^2.0.0",
				"botframework-schema": "^4.0.8",
				"jsonwebtoken": "8.0.1",
				"ms-rest-js": "0.2.8",
				"ms-rest-azure": "^2.5.0",
				"request": "2.83.0",
				"rsa-pem-from-mod-exp": "^0.8.4"
			},
			"devDependencies": {
				"@types/mocha": "^2.2.47",
				"codelyzer": "^4.1.0",
				"mocha": "^5.0.0",
				"nyc": "^11.4.1",
				"dotenv": "^5.0.1",
				"should": "^13.2.3",
				"source-map-support": "^0.5.3",
				"ts-node": "^4.1.0"
			},
			"_hasShrinkwrap": false,
			"directories": {},
			"dist": {
				"shasum": "3737c15a88a6afb0c40d5d26eb9636911a2f41df",
				"tarball": "https://registry.npmjs.org/botframework-connector/-/botframework-connector-4.0.8.tgz",
				"integrity": "sha512-tNJrhizeH3bcm3KfZ8QSWE/Yi8jvO1HUiGMdvX0pRmvTU9KYEYxrL0lJ8M37Vah6n8k5uZ+CuotmM3VdBha3dA==",
				"fileCount": 91,
				"unpackedSize": 805814,
				"npm-signature": "-----BEGIN PGP SIGNATURE-----\r\nVersion: OpenPGP.js v3.0.4\r\nComment: https://openpgpjs.org\r\n\r\nwsFcBAEBCAAQBQJbxjuECRA9TVsSAnZWagAADMUP/0FyB3zS7BEnppS5Pz6L\n9bZTXBHmaceiaqdLKy5K3wtBnSSwN3jnFOvgg5Gr91XopTl5pel16ISMDnAB\nXjoyLdoI3fl3Xs4piWVRaPtptd6ikt0MIiqfCP0Vrb0nQXXTfd0CP41dsb+F\nd7QqZS6unTXHRSzQNpOAlhCvHv/rKax7uuG0N2a/95mEAI/0O1aFlMo/H/af\nEpRRqDwM3LmKfgMDH5itzXQ3ej+xYhfe+QDxiPRFK0Zg0f/uE5sElMljJym8\nzS4a7MQRDOXGDOtTDDuSqA1Fid8AGy4lpfUIMo/VOoaSef+996zEL419lYkv\nWyc1IMATBo0zOpwV4+UVJAMYUJjCMRao5oysZc6Le0F81h2wru/eYo1yn23B\ntI37OcFN1hqNmiXIulEd3GwOXSW1UEkgol91gp3u+yfG4DFeGI0gKp1LhYWB\n6WzWfpz/trpXe6EgTcVInl5xYGMwIudIvpZVu2kAM6ZDVkUpxwTF+XK5lM04\nkPjxk/Fo+unB6HgJ9lK7BavnuDIVBEAlhtKRjOCb0i/pSIysLcEtHSAnFQKI\nJVWAYAkwiRzpA7gw6euk/Dg9rQVbDnAZ/fx9Vv/1inPOAzvbUcwDK0HPSom7\nXM+K1xncJOEKPTlgAqmun0qKecGwfwjKCYVOayWHfGhQQkGb/vQpPpqt+Z4S\nhyyv\r\n=m3f+\r\n-----END PGP SIGNATURE-----\r\n"
			}
		},
		"4.1.3": {
			"name": "botframework-connector",
			"version": "4.1.3",
			"dependencies": {
				"@types/jsonwebtoken": "7.2.8",
				"@types/node": "^9.3.0",
				"@types/request": "^2.47.0",
				"base64url": "^3.0.0",
				"botframework-schema": "^4.1.3",
				"jsonwebtoken": "8.0.1",
				"ms-rest-azure": "^2.5.0",
				"ms-rest-js": "0.2.8",
				"request": "^2.87.0",
				"rsa-pem-from-mod-exp": "^0.8.4"
			},
			"devDependencies": {
				"@types/mocha": "^2.2.47",
				"codelyzer": "^4.1.0",
				"mocha": "^5.2.0",
				"nyc": "^11.4.1",
				"dotenv": "^5.0.1",
				"should": "^13.2.3",
				"source-map-support": "^0.5.3",
				"ts-node": "^4.1.0"
			},
			"_hasShrinkwrap": false,
			"directories": {},
			"dist": {
				"shasum": "57ed362f782e2446eb1656ec9182e4a1f61a7dee",
				"tarball": "https://registry.npmjs.org/botframework-connector/-/botframework-connector-4.1.3.tgz",
				"integrity": "sha512-6Zc4KG3Mm9p81uAavbqEbq/A5dvK+5pvov3uUiSM42zp+ljqdZXnlhFNsQq0hrSk0HgKjQLdMBdECa9PXgF1rQ==",
				"fileCount": 91,
				"unpackedSize": 798166,
				"npm-signature": "-----BEGIN PGP SIGNATURE-----\r\nVersion: OpenPGP.js v3.0.4\r\nComment: https://openpgpjs.org\r\n\r\nwsFcBAEBCAAQBQJb2exiCRA9TVsSAnZWagAANx0P/2ApfqkGkLrwxqCV8cmm\nWECCvxkgiv8Jkbymk5fVedj7K3orK19ahtFQChLUqDuB5y+iUsSL8N+hs1mE\n2iK+Y5hlo9L1082AaoFZqBPzuLqxeRDmZo2JJjjyAKbYVBt2ScGDX4lDNqFU\nC/xRJPkcwZGeToiQM3dMGPbYVH+g5iF1+X9cddKqzhsx4jUnlh6e7vTfgxzc\n8Rog5Pu96AZXt4eVaFzh0u5FcAuhUtbDnq+BkBekXnqxMDSd4cX1zMWXXu1/\nlm5V97mWxoHFSTjr07GX7p+WOqb7Al695BDEmoZH4iWbbOhuQclQ2gHIAtpN\nd0hPZfhj+UloN239QMR9Rta05+gqyyBQ2tO1Ps0fQ4pk3yORgVHKMdgMG63z\nve8ryEsMkeB+LTu/k00xJsZ79hakUsUnZgmS6Ra3DLt77isEpXxqLaeJSEP4\nuF0tUC4yTgVg3Uj8moPLWIp/Z5KfRp37rOK4mOG8uV8zsinRyMxt17r47sPX\nSBVScoABpMfs2epeh2zBlmsx8j5eSRweHYAPeeIS+RwG9wdEwXri0gPNMwaW\ndTMXTWDZsoKyFo4ADlNWVG268Ap8qb38rF1gBz/FXxIsomTXAPA1vwkLxNAG\nUeFgeAn6nifJ0xKrwqmUq+fZV9x/BegLwxgPq0SjBfRSlLByv4GEFkhvifll\nUIaL\r\n=BuUa\r\n-----END PGP SIGNATURE-----\r\n"
			}
		},
		"4.1.5": {
			"name": "botframework-connector",
			"version": "4.1.5",
			"dependencies": {
				"@types/jsonwebtoken": "7.2.8",
				"@types/node": "^9.3.0",
				"@types/request": "^2.47.0",
				"base64url": "^3.0.0",
				"botframework-schema": "^4.1.5",
				"jsonwebtoken": "8.0.1",
				"ms-rest-azure-js": "^1.0.176",
				"ms-rest-js": "^1.0.455",
				"request": "^2.87.0",
				"rsa-pem-from-mod-exp": "^0.8.4"
			},
			"devDependencies": {
				"@types/mocha": "^2.2.47",
				"codelyzer": "^4.1.0",
				"dotenv": "^5.0.1",
				"mocha": "^5.2.0",
				"nyc": "^11.4.1",
				"should": "^13.2.3",
				"source-map-support": "^0.5.3",
				"ts-node": "^4.1.0"
			},
			"_hasShrinkwrap": false,
			"directories": {},
			"dist": {
				"shasum": "5d1d61fe7610a98b0d9a832f391ef1694349da3c",
				"tarball": "https://registry.npmjs.org/botframework-connector/-/botframework-connector-4.1.5.tgz",
				"integrity": "sha512-fbCh+j16a3/Ylh8gm/2UnXJ02CdD5KBWdBNevMEoRZpcYUkSgcYUtKCVdeaRWQauTKFYO19KNcuBMMpLvpfnRg==",
				"fileCount": 147,
				"unpackedSize": 492041,
				"npm-signature": "-----BEGIN PGP SIGNATURE-----\r\nVersion: OpenPGP.js v3.0.4\r\nComment: https://openpgpjs.org\r\n\r\nwsFcBAEBCAAQBQJb4Nh7CRA9TVsSAnZWagAASbsP/3ufMhKMCeSaB32BuGyJ\n0a3fLMGo1Cn4idzeWlL9SQ2ABDA42jbrbyntUGABP4jmO6hiRb6nkYY+Or8W\nqn2vB0csYbZJ5cyE5Acr+5Fhyc3wlS6c0woKoZxdxdmuv13Ir/YlKOh49KqU\nzhfJZ/PDH20XTqtK+aprNwv3JsbJ2Ez7L3lFcbLj9JoZaa+4UybBWHCbWe27\nLft491wZs6WT6oRVpKUzI09BDw+HBsDvC0/7ptiEzNfhkxWyQUR6V8Y3JHgs\nGNojF3VUlWQvuDU1viiXv5RetLXP/t5YOl1vtlN4ZVndqF4O6326JNXyPS/J\n4uMMV44cePQUFBnkP0mtBLZW9K7mNt+CffP6gk56cN7g6HTtVXdyXXdqnhJy\nmISKOuYc958b7Gl0v3jcRZSDDWiTEzNyKAa6KDi6v/3BZMU8dQgJLPKOqXnj\n/L/vAAKnA6uxSmD0yXc2WPLBTHl/PG9QFFfN7rw09qQrW6N+CuAljYKsp7zy\n8K55sShV33t5pLBdgFIKi9/RLP/ywzBR+Io75DrtMzlQRE1MaboimbS6CBzJ\n/8Dvbg5OzPUrHCLOWx5Z9lpUB2ANVvb/VLp9niJQG+oayPe4W/ByzEVbUEbe\nUIzjO8+ffk9pEgiAXMjpwJooUw7Nm6xqCLuKeNj3AUKSBsfssntelrb29dE3\nJ3eN\r\n=AriZ\r\n-----END PGP SIGNATURE-----\r\n"
			}
		},
		"4.1.6": {
			"name": "botframework-connector",
			"version": "4.1.6",
			"dependencies": {
				"@types/jsonwebtoken": "7.2.8",
				"@types/node": "^9.3.0",
				"@types/request": "^2.47.0",
				"base64url": "^3.0.0",
				"botframework-schema": "^4.1.6",
				"jsonwebtoken": "8.0.1",
				"ms-rest-azure-js": "1.0.176",
				"ms-rest-js": "1.0.455",
				"request": "^2.87.0",
				"rsa-pem-from-mod-exp": "^0.8.4"
			},
			"devDependencies": {
				"@types/mocha": "^2.2.47",
				"codelyzer": "^4.1.0",
				"dotenv": "^5.0.1",
				"mocha": "^5.2.0",
				"nyc": "^11.4.1",
				"should": "^13.2.3",
				"source-map-support": "^0.5.3",
				"ts-node": "^4.1.0"
			},
			"_hasShrinkwrap": false,
			"directories": {},
			"dist": {
				"shasum": "b7f9fc520d94aa0692a48cddb795d6f1e0d32964",
				"tarball": "https://registry.npmjs.org/botframework-connector/-/botframework-connector-4.1.6.tgz",
				"integrity": "sha512-avPyvI/ZRCZIrawItmLkz2Aa2Je+SCUowRTS8wyllBFMMzIj/6QmgVoiSMV6IKoTJEN6nhh4FRAa9U8V5n3JRw==",
				"fileCount": 147,
				"unpackedSize": 492039,
				"npm-signature": "-----BEGIN PGP SIGNATURE-----\r\nVersion: OpenPGP.js v3.0.4\r\nComment: https://openpgpjs.org\r\n\r\nwsFcBAEBCAAQBQJb8JvXCRA9TVsSAnZWagAA5ogP/1kXcGXoWxeMKXcH7eHv\nNSq8N6hwh130oWmQGu0+NwXLrTUi1LtZkcopw48DAZBP53xJ/4WwfZTl3mx7\nDZ9BNHQCbiIBeka74WWB9rKGigbTF2G4HWuJLe6FfweoW1wh10x36sKD6F4E\n7R97VdEA41sPPJVzvwDy5QD/s14pthqeJlDY8t4WczqvgD81rSIAWt7gVr/d\nD4Q2mzxhuNOhmlTOwlRlkzkkJ+7BUwbmTf2rOdkgh5DUGsmAaepFAat5Ioaw\nJV+Q7coIXwz0QLhoKn/kP4j0wb2dFsEwjpsAl6YW4alozya5bR5LiNHSGVTN\nKVjIC0+hmK5J4iLGwxOoiDMvxgQJZV6BiZFmyZ3kb+htEANe3ksa2Kdwg8Xq\nF8a5b6vB820U97q8xADqiJoqd/yQOvVFyGK8vJ0yCs0LPSPzdnGJnXlMbhEF\niXA4zIR57Tl/BYNR3Jky0GTmO3ut+5gCLBhX8CHIgqCzDtuKOhR7W06EDRB4\n8i6zidY0iM1H8igCubaIoSr+mhFLxBJYzNCr3r9RGBuPNyQ9xsNbIZ+cz4AK\nnK6alAcGsR9rV18/k1tMujHtdABSb2zz3VuKgKiywAZ6rEZGneaBGJy+AU1H\n0OKW2Ttnmpj7+KQzkSbgxPOC0oiftQauQOt7oLClMgQ23hiE+LVn3PVbSU6m\nSNrp\r\n=0h0+\r\n-----END PGP SIGNATURE-----\r\n"
			}
		},
		"4.1.7": {
			"name": "botframework-connector",
			"version": "4.1.7",
			"dependencies": {
				"@types/jsonwebtoken": "7.2.8",
				"@types/node": "^9.3.0",
				"@types/request": "^2.47.0",
				"base64url": "^3.0.0",
				"botframework-schema": "^4.1.7",
				"jsonwebtoken": "8.0.1",
				"ms-rest-azure-js": "1.0.176",
				"ms-rest-js": "1.0.455",
				"request": "^2.87.0",
				"rsa-pem-from-mod-exp": "^0.8.4"
			},
			"devDependencies": {
				"@types/mocha": "^2.2.47",
				"codelyzer": "^4.1.0",
				"dotenv": "^5.0.1",
				"mocha": "^5.2.0",
				"nyc": "^11.4.1",
				"should": "^13.2.3",
				"source-map-support": "^0.5.3",
				"ts-node": "^4.1.0"
			},
			"_hasShrinkwrap": false,
			"directories": {},
			"dist": {
				"shasum": "d9012561ebcd82e2bfe9d45874947db92ee7ded9",
				"tarball": "https://registry.npmjs.org/botframework-connector/-/botframework-connector-4.1.7.tgz",
				"integrity": "sha512-aIGY0acc/cMxmg1o+06HqReOjNC8qxbmPJDg+wDgaAwr85bSrDZE1CbyITcj2OqPG/QQ7VM3YzpPAZPlKkDWoQ==",
				"fileCount": 147,
				"unpackedSize": 492039,
				"npm-signature": "-----BEGIN PGP SIGNATURE-----\r\nVersion: OpenPGP.js v3.0.4\r\nComment: https://openpgpjs.org\r\n\r\nwsFcBAEBCAAQBQJb/H+ECRA9TVsSAnZWagAAuAkP/25rUCaC5SV5lkTCrdmg\nueZi4JZM1gv9n3Pt3rxziM8/grw9V3j4yAM0xNkuNFRvwwAKpI+xdi5eazOT\nPBPUY6FaMzpcmsSZ01kg4Kt2/6rD6QOQmny1lkGNTjTki8Z2Hfaw3AWGaidq\n290lFl/fmz3Rh4+jHEEhigCzDtbp1syaID0+ZgdujqHAZJN2CwS/zD4Nxe9E\nTk5tnYZN0hJoHJXsOcrX956oAbNXf8hoembvAej2jeNrhKortEG3VpbGjJS8\n+AQEf2MI2XCjIVCRM7T6eh00sVyJgdBSqIpKUHQhsP9ctp4SUKjG3UAZ7d2j\nZlXWpYT/fRH+EEROijzB4pv31/w7xgdtyr2Io9i72kY0dZZth6Ut3xIR0xf5\n1HTtEnb7UW/Muz0A2yAJYbCLxxkKsrxJDxHSglui/n6VyCw1uGbUEKgs8DkH\nRK0r2SgMB/XzoPAP8olf+iE0EcfqQ2f5hUBXmFdaL7iczzb6qUvy9GvbgqLb\nck6jyR0sqRnJ+hjVmqIIVDGjFqse7fdL6EAYD3HJREqqvXLQC9phZsKfQT1x\nyxvkkl7G+ITyCkZ9AlO4Xba0JJbli2aA67y88p50cIOSFzFSRnUV+e8Rq46T\n4vicc4L0PHOxJ6+xGvi7e83UAAmaMXYCsCahMk56Oij0eYwNVwgNylmKQVfV\nx2U4\r\n=ebCi\r\n-----END PGP SIGNATURE-----\r\n"
			}
		},
		"4.2.0": {
			"name": "botframework-connector",
			"version": "4.2.0",
			"dependencies": {
				"@types/jsonwebtoken": "7.2.8",
				"@types/node": "^9.3.0",
				"base64url": "^3.0.0",
				"botframework-schema": "^4.2.0",
				"form-data": "^2.3.3",
				"jsonwebtoken": "8.0.1",
				"ms-rest-azure-js": "1.0.176",
				"ms-rest-js": "1.0.455",
				"nock": "^10.0.3",
				"node-fetch": "^2.2.1",
				"rsa-pem-from-mod-exp": "^0.8.4"
			},
			"devDependencies": {
				"@types/mocha": "^2.2.47",
				"codelyzer": "^4.1.0",
				"dotenv": "^5.0.1",
				"mocha": "^5.2.0",
				"nyc": "^11.4.1",
				"should": "^13.2.3",
				"source-map-support": "^0.5.3",
				"ts-node": "^4.1.0"
			},
			"_hasShrinkwrap": false,
			"directories": {},
			"dist": {
				"shasum": "e396a790796ec731ee85ae2ac1f7c0fa7662ae43",
				"tarball": "https://registry.npmjs.org/botframework-connector/-/botframework-connector-4.2.0.tgz",
				"integrity": "sha512-DQtBpB4a6i/lbVBEkYS9IB0WAGJeCY04EiCl1yeh7F9K6uSwE78nNFXJtsWam1PGsinvMwHIHvFyUF5GorUgkA==",
				"fileCount": 147,
				"unpackedSize": 493466,
				"npm-signature": "-----BEGIN PGP SIGNATURE-----\r\nVersion: OpenPGP.js v3.0.4\r\nComment: https://openpgpjs.org\r\n\r\nwsFcBAEBCAAQBQJcEBETCRA9TVsSAnZWagAAJooQAI2qtXUfCcrkSpA9UKhq\nBfdJx4dXT/YxQhDPvWP2m5qHqAEyHq35ejaCcUQhJV3zTQtY98VgbqGW2/EW\nI46ZP+m38F8kd96i1kw8Pcp589wT32SfXDkR/Uu953oIxv0TD10ohnznyQ33\nbA7y2lc9phDNpgrFGhgz9nv2zCc/mmubJXBojspVdqSlHBg1id+4/KFvrDnT\nRexpB2UYJFFrtRkYnJ2X4srXPkVBSy2IdBJwD534X6xwx77/h9Ep/Q693v7K\nZ3rMgab2x/exR8sgtLD7mMyJj06t0qVX4SgGkCoVpnfHxEO1yoe/SPVRUWgi\nnIIu9CJ+JaoERcUtEXgXBV+m9XZ5O6fQHreeMmCxiQY99eyTReOqv73HMbZo\nqrs33W/Vs8MTnFqjK7e25eRK/kEhIpNCURTiRdK055aTktXr98mGDh2e1k1r\nN6XteBaYuXNgS2Q3imhSuGqQAT/FeSO47qnJVUwCiSklLaVMCGNlQX+t5so+\nIIsCDbcUlY8jyjd9555zDGiMAA2DETHaXSM1mhBXymLy2TMcZAyS0QJloVjN\nyF0fS9dX6nY4vy2tlLnmCS+TpmatxX2do1hwQG49phbyEk5cRoOYm/Blk4y2\naS5X3LIKUWQ2MicOyq9/nRTBKGYb0r5y5nGbiHU/iEHvQVXh+S2HuAMPNGMh\ncesv\r\n=nWHF\r\n-----END PGP SIGNATURE-----\r\n"
			}
		},
		"4.2.1": {
			"name": "botframework-connector",
			"version": "4.2.1",
			"dependencies": {
				"@types/jsonwebtoken": "7.2.8",
				"@types/node": "^9.3.0",
				"base64url": "^3.0.0",
				"botframework-schema": "^4.2.1",
				"form-data": "^2.3.3",
				"jsonwebtoken": "8.0.1",
				"ms-rest-azure-js": "1.0.176",
				"ms-rest-js": "1.0.455",
				"nock": "^10.0.3",
				"node-fetch": "^2.2.1",
				"rsa-pem-from-mod-exp": "^0.8.4"
			},
			"devDependencies": {
				"@types/mocha": "^2.2.47",
				"codelyzer": "^4.1.0",
				"dotenv": "^5.0.1",
				"mocha": "^5.2.0",
				"nyc": "^11.4.1",
				"should": "^13.2.3",
				"source-map-support": "^0.5.3",
				"ts-node": "^4.1.0"
			},
			"_hasShrinkwrap": false,
			"directories": {},
			"dist": {
				"shasum": "f90bd907ee09b8196acc9880ec4f5927e759e591",
				"tarball": "https://registry.npmjs.org/botframework-connector/-/botframework-connector-4.2.1.tgz",
				"integrity": "sha512-O2RmSG4AFyNc7h9zD2a7kdIBw8jF3Thpl8Pwfs/BpKGhRrCIJAMasV0+UbIV2Iwi2NEl7WzdpXjUsnpmB57XgQ==",
				"fileCount": 147,
				"unpackedSize": 493461,
				"npm-signature": "-----BEGIN PGP SIGNATURE-----\r\nVersion: OpenPGP.js v3.0.4\r\nComment: https://openpgpjs.org\r\n\r\nwsFcBAEBCAAQBQJcVNw/CRA9TVsSAnZWagAA/V0P/iOqXUeXEIDnNkupq1uB\nuEwU70me9Lz1nriUUZaiNxbm2TbcotxpZDT8As/RTsWuS69qe/lW+3zw4yzd\nrssBR8WN6bRTJkBtjeYzTEgF8bFzk8ErLl+dAEjmvL4zqNBFswQr+30g840+\nZ1KLA9Veth85V4P4+2ebFeq6gem1GmBB9js4ycSpFy3FqhM25FOpz5yMxTYE\nRXg2wTmyVmbWdRXsxczKishp8MUx0y6qA6bppBg1xYKPiOQuWspV7em71KnG\nmqKE7onRzwmXuutuFixnZK/TGrimHPzwVfeGcZxJ6XBwThztRnLCj/D4Tuuv\ngyE4uSHFP/osQ7y9Mtx5Q/qYFwPcLGwcrH5ojO6U8iEuqya2MQQXT8bvaDfH\n9FkaWLXsiHsFBcP8xP+nQColQiDOqz39c9kEO39R/QcaJGWgTlqVZnsvNFiI\nI34j1uaj25IYK0gqQTk4gGZMnlUJWjb5XO6NdmxXF3UCFFliDwtLTMScxtAH\nCaMw+4RkM5Tro+PqCP2BbaDtOlcSh2J3IEtb1btbIlkm1hGVgWWCYmX7p2Qh\n8snJn2fsQ4Da3H5bqPatWSp/QZaJwDkQ3K926PHejo8zVi+MxyJ2d+XxeAI9\n4skXYfOx7V7gY0hoMSaIoAqg6c2rpO2km4bCqUhlsL2cd0FdvzEH6G3unsqs\n3NBg\r\n=kNzO\r\n-----END PGP SIGNATURE-----\r\n"
			}
		}
	},
	"name": "botframework-connector",
	"dist-tags": {
		"preview": "4.0.0-preview1.2",
		"latest": "4.2.1"
	},
	"modified": "2019-02-01T23:54:41.274Z",
	"cachedAt": 1551462411606
}
